{
  "firmwareId": "7zabZ0",
  "buildResult": "success",
  "releaseBuildRevision": 7,
  "buildTimestamp": "2022-08-07T09:10:12.846Z",
  "storageFormatRevision": 6,
  "messageProtocolRevision": 5,
  "profileBinaryFormatRevision": 5,
  "configParametersRevision": 5,
  "flashUsage": 3.69,
  "ramUsage": 5.25,
  "firmwareFileSize": 155136,
  "firmwareBinaryFileMD5": "8b76812dece917c6a2d2a921052d15b3",
  "variationName": "rev2_rp",
  "targetDevice": "rp2040",
  "firmwareFileName": "sp2104_rev2_rp.uf2"
}